dataclay/__init__.py
dataclay/alien.py
dataclay/annotated.py
dataclay/config.py
dataclay/data_manager.py
dataclay/dataclay_object.py
dataclay/event_loop.py
dataclay/exceptions.py
dataclay/lock_manager.py
dataclay/runtime.py
dataclay/stub.py
dataclay/backend/__init__.py
dataclay/backend/__main__.py
dataclay/backend/api.py
dataclay/backend/client.py
dataclay/backend/servicer.py
dataclay/client/__init__.py
dataclay/client/api.py
dataclay/contrib/__init__.py
dataclay/contrib/collections.py
dataclay/contrib/dummy_persistent_block.py
dataclay/contrib/dummy_pycompss.py
dataclay/contrib/kafka.py
dataclay/contrib/mqtt.py
dataclay/contrib/nvm.py
dataclay/contrib/persistent_block.py
dataclay/contrib/splitting.py
dataclay/contrib/zenoh_module.py
dataclay/contrib/dataclay_dummy/__init__.py
dataclay/contrib/modeltest/__init__.py
dataclay/contrib/modeltest/alien.py
dataclay/contrib/modeltest/apirest.py
dataclay/contrib/modeltest/classes.py
dataclay/contrib/modeltest/compss.py
dataclay/contrib/modeltest/family.py
dataclay/contrib/modeltest/matrix.py
dataclay/contrib/modeltest/remote.py
dataclay/control/ctl.py
dataclay/metadata/__init__.py
dataclay/metadata/__main__.py
dataclay/metadata/api.py
dataclay/metadata/client.py
dataclay/metadata/kvdata.py
dataclay/metadata/redismanager.py
dataclay/metadata/servicer.py
dataclay/paraver/__init__.py
dataclay/paraver/__main__.py
dataclay/proxy/__init__.py
dataclay/proxy/__main__.py
dataclay/proxy/base_classes.py
dataclay/proxy/exceptions.py
dataclay/proxy/servicer.py
dataclay/utils/__init__.py
dataclay/utils/backend_clients.py
dataclay/utils/decorators.py
dataclay/utils/metrics.py
dataclay/utils/serialization.py
dataclay/utils/telemetry.py
dataclay/utils/uuid.py
storage/__init__.py
storage/api.py
storage/models/__init__.py
storage/models/storagedict.py
storage/models/storagelist.py
dataclay/proto/backend/backend_pb2.py
dataclay/proto/backend/backend_pb2_grpc.py
dataclay/proto/common/common_pb2.py
dataclay/proto/common/common_pb2_grpc.py
dataclay-4.3.0.dist-info/METADATA
dataclay-4.3.0.dist-info/WHEEL
dataclay-4.3.0.dist-info/entry_points.txt
dataclay-4.3.0.dist-info/licenses/LICENSE.txt
dataclay-4.3.0.dist-info/RECORD
